<?xml version="1.0" encoding="UTF-8"?>
<faces-config>
  <!-- ham & beans -->
  <managed-bean>
    <managed-bean-name>nav</managed-bean-name>
    <managed-bean-class>org.openntf.uikit.Navigation
		</managed-bean-class>
    <managed-bean-scope>view</managed-bean-scope>
  </managed-bean>
  <!-- custom renderer -->
  <render-kit>
    <renderer>
      <component-family>com.ibm.xsp.Tag</component-family>
      <renderer-type>uikit.Panel</renderer-type>
      <renderer-class>org.openntf.uikit.renderer.Panel
			</renderer-class>
    </renderer>
    <renderer>
      <component-family>javax.faces.Panel
			</component-family>
      <renderer-type>uikit.Panel</renderer-type>
      <renderer-class>org.openntf.uikit.renderer.Panel
			</renderer-class>
    </renderer>
  </render-kit>
  <!--AUTOGEN-START-BUILDER: Automatically generated by IBM Domino Designer. Do not modify.-->
  <!--AUTOGEN-END-BUILDER: End of automatically generated section-->
</faces-config>
